sql_error_categorizer/__init__.py
sql_error_categorizer/sql_errors.py
sql_error_categorizer/catalog/__init__.py
sql_error_categorizer/catalog/catalog.py
sql_error_categorizer/catalog/column.py
sql_error_categorizer/catalog/constraint.py
sql_error_categorizer/catalog/schema.py
sql_error_categorizer/catalog/table.py
sql_error_categorizer/catalog/builder/__init__.py
sql_error_categorizer/catalog/builder/queries.py
sql_error_categorizer/detectors/__init__.py
sql_error_categorizer/detectors/base.py
sql_error_categorizer/detectors/complications.py
sql_error_categorizer/detectors/logical.py
sql_error_categorizer/detectors/semantic.py
sql_error_categorizer/detectors/syntax.py
sql_error_categorizer/query/__init__.py
sql_error_categorizer/query/extractors.py
sql_error_categorizer/query/query.py
sql_error_categorizer/query/smt.py
sql_error_categorizer/query/tokenized_sql.py
sql_error_categorizer/query/set_operations/__init__.py
sql_error_categorizer/query/set_operations/binary_set_operation.py
sql_error_categorizer/query/set_operations/select.py
sql_error_categorizer/query/set_operations/set_operation.py
sql_error_categorizer/query/typechecking/__init__.py
sql_error_categorizer/query/typechecking/base.py
sql_error_categorizer/query/typechecking/binary_ops.py
sql_error_categorizer/query/typechecking/functions.py
sql_error_categorizer/query/typechecking/predicates.py
sql_error_categorizer/query/typechecking/primitives.py
sql_error_categorizer/query/typechecking/queries.py
sql_error_categorizer/query/typechecking/types.py
sql_error_categorizer/query/typechecking/unary_ops.py
sql_error_categorizer/query/typechecking/util.py
sql_error_categorizer/util/__init__.py
sql_error_categorizer/util/sql.py
sql_error_categorizer/util/tokens.py
sql_error_categorizer/util/ast/__init__.py
sql_error_categorizer/util/ast/column.py
sql_error_categorizer/util/ast/function.py
sql_error_categorizer/util/ast/subquery.py
sql_error_categorizer/util/ast/table.py
sql_error_categorizer-0.1.10.dist-info/METADATA
sql_error_categorizer-0.1.10.dist-info/WHEEL
sql_error_categorizer-0.1.10.dist-info/licenses/LICENSE
sql_error_categorizer-0.1.10.dist-info/RECORD
