Metadata-Version: 2.4
Name: sql_error_categorizer
Version: 0.1.10
Summary: This project analyses SQL statements and labels possible errors or complications.
Project-URL: Repository, https://github.com/DavidePonzini/sql_error_categorizer
Project-URL: Documentation, https://sql-error-categorizer.readthedocs.io/en/latest/index.html
Project-URL: Bug Tracker, https://github.com/DavidePonzini/sql_error_categorizer/issues
Author-email: Davide Ponzini <davide.ponzini95@gmail.com>
License-File: LICENSE
Classifier: License :: OSI Approved :: MIT License
Classifier: Operating System :: OS Independent
Classifier: Programming Language :: Python :: 3
Requires-Python: >=3.11
Requires-Dist: psycopg2
Requires-Dist: python-dateutil
Requires-Dist: pyyaml
Requires-Dist: sqlglot
Requires-Dist: sqlparse
Requires-Dist: z3-solver
